<?xml version="1.0" encoding="UTF-8" standalone="yes"?>
 

<item>
<title>--- documentales ---</title>
<thumbnail></thumbnail>
<fanart></fanart>
<link>http://ignoreme</link>
<externallink></externallink>
</item>

<item>
<title>[COLOR lime]•[/COLOR]Videos de pesca</title>
<thumbnail></thumbnail>
<fanart></fanart>
<link>http://ignoreme</link>
<externallink>https://raw.githubusercontent.com/brujotv/puertotv/master/pesca.xml</externallink>
</item>

 <item>
<title>[COLOR lime]•[/COLOR]Videos de caza</title>
<thumbnail>http://estesobdb.com/adm5/wp-content/uploads/2013/10/pagina-en-construccion.jpg</thumbnail>
<fanart>http://estesobdb.com/adm5/wp-content/uploads/2013/10/pagina-en-construccion.jpg</fanart>
<link>http://ignoreme</link>
<externallink></externallink>
</item>


