<?xml version="1.0" encoding="UTF-8" standalone="yes"?>




<item><title>[COLOR lime]•[/COLOR] TIPARRACO SA (CAMARAS OCULTAS)</title>
<link>$doregex[makelist]</link>
<regex><name>makelist</name>
<listrepeat><![CDATA[
<title>[makelist.param1]</title>
<link>plugin://plugin.video.youtube/play/?video_id=[makelist.param2]</link>
<thumbnail>https://i.ytimg.com/vi/[makelist.param2]/hqdefault.jpg</thumbnail>
]]></listrepeat>
<expres>title="(.*?)".*?watch\?v=(.*?)[",&amp;]</expres>
<page>https://www.youtube.com/channel/UCW3iVpk5l1EuJc8p2EIAFRQ</page>
</regex>
<thumbnail>https://yt3.ggpht.com/-27GCu4dyFFU/AAAAAAAAAAI/AAAAAAAAAAA/UbORcYn5_rQ/s240-c-k-no-mo-rj-c0xffffff/photo.jpg</thumbnail></item>

<item><title>[COLOR lime]•[/COLOR] Todo veo</title>
<link>$doregex[makelist]</link>
<regex><name>makelist</name>
<listrepeat><![CDATA[
<title>[makelist.param1]</title>
<link>plugin://plugin.video.youtube/play/?video_id=[makelist.param2]</link>
<thumbnail>https://i.ytimg.com/vi/[makelist.param2]/hqdefault.jpg</thumbnail>
]]></listrepeat>
<expres>title="(.*?)".*?watch\?v=(.*?)[",&amp;]</expres>
<page>https://www.youtube.com/channel/UCsMSfkQW-02cy2T-XUjvhdg</page>
</regex>
<thumbnail>https://yt3.ggpht.com/-kt4PUO3clYA/AAAAAAAAAAI/AAAAAAAAAAA/4JofuJeMyPA/s240-c-k-no-mo-rj-c0xffffff/photo.jpg</thumbnail></item>

<item><title>[COLOR lime]•[/COLOR] El jueves</title>
<link>$doregex[makelist]</link>
<regex><name>makelist</name>
<listrepeat><![CDATA[
<title>[makelist.param1]</title>
<link>plugin://plugin.video.youtube/play/?video_id=[makelist.param2]</link>
<thumbnail>https://i.ytimg.com/vi/[makelist.param2]/hqdefault.jpg</thumbnail>
]]></listrepeat>
<expres>title="(.*?)".*?watch\?v=(.*?)[",&amp;]</expres>
<page>https://www.youtube.com/channel/UCPbXnQrEwH_UnNb45bm1iKw</page>
</regex>
<thumbnail>https://yt3.ggpht.com/-cUWFj_D0xTE/AAAAAAAAAAI/AAAAAAAAAAA/qR02aYgr9F8/s240-c-k-no-mo-rj-c0xffffff/photo.jpg</thumbnail></item>

<item><title>[COLOR lime]•[/COLOR] Don risas</title>
<link>$doregex[makelist]</link>
<regex><name>makelist</name>
<listrepeat><![CDATA[
<title>[makelist.param1]</title>
<link>plugin://plugin.video.youtube/play/?video_id=[makelist.param2]</link>
<thumbnail>https://i.ytimg.com/vi/[makelist.param2]/hqdefault.jpg</thumbnail>
]]></listrepeat>
<expres>title="(.*?)".*?watch\?v=(.*?)[",&amp;]</expres>
<page>https://www.youtube.com/channel/UCfs14tNr0tfJfiX5cvUsO7w</page>
</regex>
<thumbnail>https://yt3.ggpht.com/-teyt_wNsF8Q/AAAAAAAAAAI/AAAAAAAAAAA/VzfDf3gVSQM/s240-c-k-no-mo-rj-c0xffffff/photo.jpg</thumbnail></item>


<item><title>[COLOR lime]•[/COLOR] Top treding video</title>
<link>$doregex[makelist]</link>
<regex><name>makelist</name>
<listrepeat><![CDATA[
<title>[makelist.param1]</title>
<link>plugin://plugin.video.youtube/play/?video_id=[makelist.param2]</link>
<thumbnail>https://i.ytimg.com/vi/[makelist.param2]/hqdefault.jpg</thumbnail>
]]></listrepeat>
<expres>title="(.*?)".*?watch\?v=(.*?)[",&amp;]</expres>
<page>https://www.youtube.com/channel/UCOJzAHs3KOn9rwdxWJB7UAQ</page>
</regex>
<thumbnail>https://yt3.ggpht.com/-VdJrmbKYLIQ/AAAAAAAAAAI/AAAAAAAAAAA/iwpiP-wvhL4/s240-c-k-no-mo-rj-c0xffffff/photo.jpg</thumbnail></item>

<item><title>[COLOR lime]•[/COLOR] Muertos de risas</title>
<link>$doregex[makelist]</link>
<regex><name>makelist</name>
<listrepeat><![CDATA[
<title>[makelist.param1]</title>
<link>plugin://plugin.video.youtube/play/?video_id=[makelist.param2]</link>
<thumbnail>https://i.ytimg.com/vi/[makelist.param2]/hqdefault.jpg</thumbnail>
]]></listrepeat>
<expres>title="(.*?)".*?watch\?v=(.*?)[",&amp;]</expres>
<page>https://www.youtube.com/channel/UCa_sZYeCpZ-eOCtngCwENKw</page>
</regex>
<thumbnail>https://yt3.ggpht.com/-m1SbjbZ4UgQ/AAAAAAAAAAI/AAAAAAAAAAA/3HxFTOprWIs/s240-c-k-no-mo-rj-c0xffffff/photo.jpg</thumbnail></item>

<item><title>[COLOR lime]•[/COLOR] El mundo today</title>
<link>$doregex[makelist]</link>
<regex><name>makelist</name>
<listrepeat><![CDATA[
<title>[makelist.param1]</title>
<link>plugin://plugin.video.youtube/play/?video_id=[makelist.param2]</link>
<thumbnail>https://i.ytimg.com/vi/[makelist.param2]/hqdefault.jpg</thumbnail>
]]></listrepeat>
<expres>title="(.*?)".*?watch\?v=(.*?)[",&amp;]</expres>
<page>https://www.youtube.com/channel/UCbfxxmFIJGD_S6xim0EphBw</page>
</regex>
<thumbnail>https://yt3.ggpht.com/-SNzXXKxt938/AAAAAAAAAAI/AAAAAAAAAAA/v0RZUPL-WQs/s240-c-k-no-mo-rj-c0xffffff/photo.jpg</thumbnail></item>


<item><title>[COLOR lime]•[/COLOR] You jaja</title>
<link>$doregex[makelist]</link>
<regex><name>makelist</name>
<listrepeat><![CDATA[
<title>[makelist.param1]</title>
<link>plugin://plugin.video.youtube/play/?video_id=[makelist.param2]</link>
<thumbnail>https://i.ytimg.com/vi/[makelist.param2]/hqdefault.jpg</thumbnail>
]]></listrepeat>
<expres>title="(.*?)".*?watch\?v=(.*?)[",&amp;]</expres>
<page>https://www.youtube.com/channel/UCK1zoWk1o0kcdMTwlfXc_iw</page>
</regex>
<thumbnail>https://yt3.ggpht.com/-p8EnO1lo6s8/AAAAAAAAAAI/AAAAAAAAAAA/PULb8xQL-X0/s240-c-k-no-mo-rj-c0xffffff/photo.jpg</thumbnail></item>


<item><title>[COLOR lime]•[/COLOR] You more tv</title>
<link>$doregex[makelist]</link>
<regex><name>makelist</name>
<listrepeat><![CDATA[
<title>[makelist.param1]</title>
<link>plugin://plugin.video.youtube/play/?video_id=[makelist.param2]</link>
<thumbnail>https://i.ytimg.com/vi/[makelist.param2]/hqdefault.jpg</thumbnail>
]]></listrepeat>
<expres>title="(.*?)".*?watch\?v=(.*?)[",&amp;]</expres>
<page>https://www.youtube.com/channel/UCB8HBIOYHG4xpq_puJiD2ww</page>
</regex>
<thumbnail>https://yt3.ggpht.com/-9QHCZqgvJO0/AAAAAAAAAAI/AAAAAAAAAAA/4XgrPioxyH0/s240-c-k-no-mo-rj-c0xffffff/photo.jpg</thumbnail></item>


<item><title>[COLOR lime]•[/COLOR] Vaya semanita</title>
<link>$doregex[makelist]</link>
<regex><name>makelist</name>
<listrepeat><![CDATA[
<title>[makelist.param1]</title>
<link>plugin://plugin.video.youtube/play/?video_id=[makelist.param2]</link>
<thumbnail>https://i.ytimg.com/vi/[makelist.param2]/hqdefault.jpg</thumbnail>
]]></listrepeat>
<expres>title="(.*?)".*?watch\?v=(.*?)[",&amp;]</expres>
<page>https://www.youtube.com/channel/UC_hhp2XkNwg2OkJCCva01NA/playlist/PL5Bmmf2CrzNP-IpSnRTl3tT3VU7XryjAo</page>
</regex>
<thumbnail>https://i.ytimg.com/vi/PP0WxpUaojw/mqdefault.jpg</thumbnail></item>

<item><title>[COLOR lime]•[/COLOR] Gomaespuma</title>
<link>$doregex[makelist]</link>
<regex><name>makelist</name>
<listrepeat><![CDATA[
<title>[makelist.param1]</title>
<link>plugin://plugin.video.youtube/play/?video_id=[makelist.param2]</link>
<thumbnail>https://i.ytimg.com/vi/[makelist.param2]/hqdefault.jpg</thumbnail>
]]></listrepeat>
<expres>title="(.*?)".*?watch\?v=(.*?)[",&amp;]</expres>
<page>https://www.youtube.com/channel/UCUdYzKDNcmv3zKLcH2G79GA</page>
</regex>
<thumbnail>https://yt3.ggpht.com/-F6ZFrEasgwI/AAAAAAAAAAI/AAAAAAAAAAA/efyGi8DEzwo/s240-c-k-no-mo-rj-c0xffffff/photo.jpg</thumbnail></item>


<item><title>[COLOR lime]•[/COLOR] Homo zapping</title>
<link>$doregex[makelist]</link>
<regex><name>makelist</name>
<listrepeat><![CDATA[
<title>[makelist.param1]</title>
<link>plugin://plugin.video.youtube/play/?video_id=[makelist.param2]</link>
<thumbnail>https://i.ytimg.com/vi/[makelist.param2]/hqdefault.jpg</thumbnail>
]]></listrepeat>
<expres>title="(.*?)".*?watch\?v=(.*?)[",&amp;]</expres>
<page>https://www.youtube.com/channel/UCfytAifYOmxgJs-9qi1z25Q/playlist/PLim8DeueNY_NSc0qbfzYAim5-6ejeew7G</page>
</regex>
<thumbnail>https://i.ytimg.com/vi/SLZpssah6jw/hqdefault.jpg</thumbnail></item>

<item><title>[COLOR lime]•[/COLOR] Arevalo</title>
<link>$doregex[makelist]</link>
<regex><name>makelist</name>
<listrepeat><![CDATA[
<title>[makelist.param1]</title>
<link>plugin://plugin.video.youtube/play/?video_id=[makelist.param2]</link>
<thumbnail>https://i.ytimg.com/vi/[makelist.param2]/hqdefault.jpg</thumbnail>
]]></listrepeat>
<expres>title="(.*?)".*?watch\?v=(.*?)[",&amp;]</expres>
<page>https://www.youtube.com/channel/UCbXaS-JmSy8KXZqrddsNzkQ</page>
</regex>
<thumbnail>https://i.ytimg.com/vi/wDVlxLQlNHA/hqdefault.jpg</thumbnail></item>

<item><title>[COLOR lime]•[/COLOR] Chiquito de la calzada</title>
<link>$doregex[makelist]</link>
<regex><name>makelist</name>
<listrepeat><![CDATA[
<title>[makelist.param1]</title>
<link>plugin://plugin.video.youtube/play/?video_id=[makelist.param2]</link>
<thumbnail>https://i.ytimg.com/vi/[makelist.param2]/hqdefault.jpg</thumbnail>
]]></listrepeat>
<expres>title="(.*?)".*?watch\?v=(.*?)[",&amp;]</expres>
<page>https://www.youtube.com/channel/UCwgEPBf2BDzEg56Elxh_KmA/playlist/PL2nVNrCTI9CVxnDha8paorX_YfVCLeupT</page>
</regex>
<thumbnail>https://i.ytimg.com/vi/F0X8KlS9C8w/hqdefault.jpg</thumbnail></item>

<item><title>[COLOR lime]•[/COLOR] CRUZ Y RAYA</title>
<link>$doregex[makelist]</link>
<regex><name>makelist</name>
<listrepeat><![CDATA[
<title>[makelist.param1]</title>
<link>plugin://plugin.video.youtube/play/?video_id=[makelist.param2]</link>
<thumbnail>https://i.ytimg.com/vi/[makelist.param2]/hqdefault.jpg</thumbnail>
]]></listrepeat>
<expres>title="(.*?)".*?watch\?v=(.*?)[",&amp;]</expres>
<page>https://www.youtube.com/channel/UCJySGj0HXn1oukCc2tQT9lQ/playlist/PLwpA47HIaKh0VgMzCqCPbiwD1FSBSBb6h</page>
</regex>
<thumbnail>https://i.ytimg.com/vi/aulUr3l4Xrc/hqdefault.jpg</thumbnail></item>

<item><title>[COLOR lime]•[/COLOR] Dani mateo</title>
<link>$doregex[makelist]</link>
<regex><name>makelist</name>
<listrepeat><![CDATA[
<title>[makelist.param1]</title>
<link>plugin://plugin.video.youtube/play/?video_id=[makelist.param2]</link>
<thumbnail>https://i.ytimg.com/vi/[makelist.param2]/hqdefault.jpg</thumbnail>
]]></listrepeat>
<expres>title="(.*?)".*?watch\?v=(.*?)[",&amp;]</expres>
<page>https://www.youtube.com/channel/UCrEow12VXi1GvOuGO2Rw-tA/playlist/PLkLkKqLGc8jfGCRefyC8lWEY6GUCBZFvh</page>
</regex>
<thumbnail>https://i.ytimg.com/vi/9cod_ggcFko/mqdefault.jpg</thumbnail></item>

<item><title>[COLOR lime]•[/COLOR] Dani rovira</title>
<link>$doregex[makelist]</link>
<regex><name>makelist</name>
<listrepeat><![CDATA[
<title>[makelist.param1]</title>
<link>plugin://plugin.video.youtube/play/?video_id=[makelist.param2]</link>
<thumbnail>https://i.ytimg.com/vi/[makelist.param2]/hqdefault.jpg</thumbnail>
]]></listrepeat>
<expres>title="(.*?)".*?watch\?v=(.*?)[",&amp;]</expres>
<page>https://www.youtube.com/channel/UC-S8hXOB2b8LciyYM-Mm6ag/playlist/PLm0RlnQLOTa9eZ6zYoLXw01UATxqJPxNO</page>
</regex>
<thumbnail>https://i.ytimg.com/vi/84VBPkR3rcc/mqdefault.jpg</thumbnail></item>

<item><title>[COLOR lime]•[/COLOR] Eugenio</title>
<link>$doregex[makelist]</link>
<regex><name>makelist</name>
<listrepeat><![CDATA[
<title>[makelist.param1]</title>
<link>plugin://plugin.video.youtube/play/?video_id=[makelist.param2]</link>
<thumbnail>https://i.ytimg.com/vi/[makelist.param2]/hqdefault.jpg</thumbnail>
]]></listrepeat>
<expres>title="(.*?)".*?watch\?v=(.*?)[",&amp;]</expres>
<page>https://www.youtube.com/channel/UCqntHmjvCUEBpxUmb_jMAbw</page>
</regex>
<thumbnail>https://i.ytimg.com/vi/hqicXKPkCPQ/hqdefault.jpg</thumbnail></item>

<item><title>[COLOR lime]•[/COLOR] Ernesto sevilla</title>
<link>$doregex[makelist]</link>
<regex><name>makelist</name>
<listrepeat><![CDATA[
<title>[makelist.param1]</title>
<link>plugin://plugin.video.youtube/play/?video_id=[makelist.param2]</link>
<thumbnail>https://i.ytimg.com/vi/[makelist.param2]/hqdefault.jpg</thumbnail>
]]></listrepeat>
<expres>title="(.*?)".*?watch\?v=(.*?)[",&amp;]</expres>
<page>https://www.youtube.com/channel/UCB7wtzI_6Zd9N7LAr4spe5A</page>
</regex>
<thumbnail>https://i.ytimg.com/vi/beyvu_e-xMs/mqdefault.jpg</thumbnail></item>

<item><title>[COLOR lime]•[/COLOR] Eva hache</title>
<link>$doregex[makelist]</link>
<regex><name>makelist</name>
<listrepeat><![CDATA[
<title>[makelist.param1]</title>
<link>plugin://plugin.video.youtube/play/?video_id=[makelist.param2]</link>
<thumbnail>https://i.ytimg.com/vi/[makelist.param2]/hqdefault.jpg</thumbnail>
]]></listrepeat>
<expres>title="(.*?)".*?watch\?v=(.*?)[",&amp;]</expres>
<page>https://www.youtube.com/channel/UCukPzMNIjeUYWLip5jwnkpQ</page>
</regex>
<thumbnail>https://i.ytimg.com/vi/dlfqskBZvN4/mqdefault.jpg</thumbnail></item>

<item><title>[COLOR lime]•[/COLOR] MR. BEAN</title>
<link>$doregex[makelist]</link>
<regex><name>makelist</name>
<listrepeat><![CDATA[
<title>[makelist.param1]</title>
<link>plugin://plugin.video.youtube/play/?video_id=[makelist.param2]</link>
<thumbnail>https://i.ytimg.com/vi/[makelist.param2]/hqdefault.jpg</thumbnail>
]]></listrepeat>
<expres>title="(.*?)".*?watch\?v=(.*?)[",&amp;]</expres>
<page>https://www.youtube.com/channel/UCkAGrHCLFmlK3H2kd6isipg</page>
</regex>
<thumbnail>https://yt3.ggpht.com/-FvBjR0DHn0c/AAAAAAAAAAI/AAAAAAAAAAA/1X7Fl-w2PUw/s240-c-k-no-mo-rj-c0xffffff/photo.jpg</thumbnail></item>


<item><title>[COLOR lime]•[/COLOR] Miguel gila</title>
<link>$doregex[makelist]</link>
<regex><name>makelist</name>
<listrepeat><![CDATA[
<title>[makelist.param1]</title>
<link>plugin://plugin.video.youtube/play/?video_id=[makelist.param2]</link>
<thumbnail>https://i.ytimg.com/vi/[makelist.param2]/hqdefault.jpg</thumbnail>
]]></listrepeat>
<expres>title="(.*?)".*?watch\?v=(.*?)[",&amp;]</expres>
<page>https://www.youtube.com/channel/UCwj4zLJ-dPmr3Flk46ZaD2g/playlist/PLsypPztNeC4HsYgu7JQRPExfmeqgUGEDc</page>
</regex>
<thumbnail>https://i.ytimg.com/vi/dPnpzlCc-q8/hqdefault.jpg</thumbnail></item>



<item><title>[COLOR lime]•[/COLOR] MARTES Y TRECE</title>
<link>$doregex[makelist]</link>
<regex><name>makelist</name>
<listrepeat><![CDATA[
<title>[makelist.param1]</title>
<link>plugin://plugin.video.youtube/play/?video_id=[makelist.param2]</link>
<thumbnail>https://i.ytimg.com/vi/[makelist.param2]/hqdefault.jpg</thumbnail>
]]></listrepeat>
<expres>title="(.*?)".*?watch\?v=(.*?)[",&amp;]</expres>
<page>https://www.youtube.com/channel/UCmXATQAgIe_8jfpAw8GKe5Q/playlist/PL8LrSTMHPcY4XBHzkixpwcnSjDLCIAOzL</page>
</regex>
<thumbnail>https://i.ytimg.com/vi/XWO2Vya1Btw/hqdefault.jpg</thumbnail></item>

<item>
<title>[COLOR lime]•[/COLOR] Los morancos</title>
<link>$doregex[makelist]</link>
<regex><name>makelist</name>
<listrepeat><![CDATA[
<title>[makelist.param1]</title>
<link>plugin://plugin.video.youtube/play/?video_id=[makelist.param2]</link>
<thumbnail>https://i.ytimg.com/vi/[makelist.param2]/hqdefault.jpg</thumbnail>
]]></listrepeat>
<expres>title="(.*?)".*?watch\?v=(.*?)[",&amp;]</expres>
<page>https://www.youtube.com/channel/UCpu7hTlzAJUD-_PjjiBZCZg</page>
</regex>
<thumbnail>https://yt3.ggpht.com/-S6Y9BU-c_so/AAAAAAAAAAI/AAAAAAAAAAA/OCab4riMvKQ/s240-c-k-no-mo-rj-c0xffffff/photo.jpg</thumbnail>
</item>

<item>
<title>[COLOR lime]•[/COLOR] Leo harlem</title>
<link>$doregex[makelist]</link>
<regex><name>makelist</name>
<listrepeat><![CDATA[
<title>[makelist.param1]</title>
<link>plugin://plugin.video.youtube/play/?video_id=[makelist.param2]</link>
<thumbnail>https://i.ytimg.com/vi/[makelist.param2]/hqdefault.jpg</thumbnail>
]]></listrepeat>
<expres>title="(.*?)".*?watch\?v=(.*?)[",&amp;]</expres>
<page>https://www.youtube.com/channel/UCTU-TgGJa7YSQti8Hjqdj-Q/playlist/PLwb_a0vqypdJXQAB3MDXpjW5o0DTMPG58</page>
</regex>
<thumbnail>https://i.ytimg.com/vi/JcCXXHknUbc/mqdefault.jpg</thumbnail>
</item>

<item>
<title>[COLOR lime]•[/COLOR] Jose mota</title>
<link>$doregex[makelist]</link>
<regex><name>makelist</name>
<listrepeat><![CDATA[
<title>[makelist.param1]</title>
<link>plugin://plugin.video.youtube/play/?video_id=[makelist.param2]</link>
<thumbnail>https://i.ytimg.com/vi/[makelist.param2]/hqdefault.jpg</thumbnail>
]]></listrepeat>
<expres>title="(.*?)".*?watch\?v=(.*?)[",&amp;]</expres>
<page>https://www.youtube.com/channel/UCPCJV3XMMmdQ6ZJ4JPCf2jQ</page>
</regex>
<thumbnail>https://yt3.ggpht.com/-9BqFTiBdrdo/AAAAAAAAAAI/AAAAAAAAAAA/YdgyUuQOhQ4/s240-c-k-no-mo-rj-c0xffffff/photo.jpg</thumbnail>
</item>


<item>
<title>[COLOR lime]•[/COLOR] Jose luis moreno y sus muñecos</title>
<link>$doregex[makelist]</link>
<regex><name>makelist</name>
<listrepeat><![CDATA[
<title>[makelist.param1]</title>
<link>plugin://plugin.video.youtube/play/?video_id=[makelist.param2]</link>
<thumbnail>https://i.ytimg.com/vi/[makelist.param2]/hqdefault.jpg</thumbnail>
]]></listrepeat>
<expres>title="(.*?)".*?watch\?v=(.*?)[",&amp;]</expres>
<page>https://www.youtube.com/channel/UCm7zegsp9n6RXm0ekd-Lm2A</page>
</regex>
<thumbnail>https://i.ytimg.com/vi/IE-GuJ9g4jI/hqdefault.jpg</thumbnail>
</item>

<item>
<title>[COLOR lime]•[/COLOR] Goyo jimenez</title>
<link>$doregex[makelist]</link>
<regex><name>makelist</name>
<listrepeat><![CDATA[
<title>[makelist.param1]</title>
<link>plugin://plugin.video.youtube/play/?video_id=[makelist.param2]</link>
<thumbnail>https://i.ytimg.com/vi/[makelist.param2]/hqdefault.jpg</thumbnail>
]]></listrepeat>
<expres>title="(.*?)".*?watch\?v=(.*?)[",&amp;]</expres>
<page>https://www.youtube.com/channel/UCNHPsCfNwlJQELUdbt7kuyw</page>
</regex>
<thumbnail>https://i.ytimg.com/vi/ap7F1pg5bBA/mqdefault.jpg</thumbnail>
</item>

<item><title>[COLOR lime]•[/COLOR] Monologos varios</title>
<link>$doregex[makelist]</link>
<regex><name>makelist</name>
<listrepeat><![CDATA[
<title>[makelist.param1]</title>
<link>plugin://plugin.video.youtube/play/?video_id=[makelist.param2]</link>
<thumbnail>https://i.ytimg.com/vi/[makelist.param2]/hqdefault.jpg</thumbnail>
]]></listrepeat>
<expres>title="(.*?)".*?watch\?v=(.*?)[",&amp;]</expres>
<page>https://www.youtube.com/channel/UCfs14tNr0tfJfiX5cvUsO7w/videos</page>
</regex>
<thumbnail>https://pbs.twimg.com/profile_images/529239174558138368/XoMw54lV.jpeg</thumbnail>
</item>

<item>
<title>[COLOR lime]•[/COLOR] Berto Romero: Piscinas para ricos - El Club de la Comedia</title>        
<urlsolve>https://www.youtube.com/watch?v=FtYeVs8P288&list=PLoY_dmfGHuXbjdr7tDzOiCiSMO8GPNJm9</urlsolve>
<thumbnail></thumbnail>
<fanart></fanart>
</item>

<item>
<title>[COLOR lime]•[/COLOR] Berto Romero: Fallos del lenguaje - El Club de la Comedia</title>        
<urlsolve>https://www.youtube.com/watch?v=uvqx3IIyzJ8&list=PLoY_dmfGHuXbjdr7tDzOiCiSMO8GPNJm9&index=4</urlsolve>
<thumbnail></thumbnail>
<fanart></fanart>
</item>

<item>
<title>[COLOR lime]•[/COLOR] </title>        
<urlsolve></urlsolve>
<thumbnail></thumbnail>
<fanart></fanart>
</item>

